PyWebRunner/WebDemo.py
PyWebRunner/WebRunner.py
PyWebRunner/WebTester.py
PyWebRunner/__init__.py
PyWebRunner/runner.py
PyWebRunner/utils.py
PyWebRunner-2.6.0.data/data/extensions/JSErrorCollector.crx
PyWebRunner-2.6.0.data/data/extensions/JSErrorCollector.xpi
PyWebRunner-2.6.0.dist-info/AUTHORS
PyWebRunner-2.6.0.dist-info/LICENSE
PyWebRunner-2.6.0.dist-info/METADATA
PyWebRunner-2.6.0.dist-info/WHEEL
PyWebRunner-2.6.0.dist-info/entry_points.txt
PyWebRunner-2.6.0.dist-info/top_level.txt
PyWebRunner-2.6.0.dist-info/RECORD
